cdk/__init__.py
cdk/analysis/cytosol/platereader.py
cdk/calculators/sweep_calculator.py
cdk/instruments/opentrons/config.py
cdk/instruments/opentrons/util.py
cdk/logging/__init__.py
nucleus_cdk-0.5.0rc2.dist-info/METADATA
nucleus_cdk-0.5.0rc2.dist-info/WHEEL
nucleus_cdk-0.5.0rc2.dist-info/RECORD
