Metadata-Version: 2.4
Name: nucleus-cdk
Version: 0.5.0rc2
Summary: Cell Developer Kit for building synthetic cells and cytosols.
License: MIT
Keywords: synthetic biology,synthetic cell,syncell,cellfree,nucleus,cell developer kit
Author: Anton Jackson-Smith
Author-email: anton@bnext.bio
Maintainer: Anton Jackson-Smith
Maintainer-email: anton@bnext.bio
Requires-Python: >=3.12,<4.0
Classifier: Development Status :: 3 - Alpha
Classifier: Intended Audience :: Science/Research
Classifier: License :: OSI Approved :: MIT License
Classifier: Programming Language :: Python
Classifier: Programming Language :: Python :: 3
Classifier: Programming Language :: Python :: 3.12
Classifier: Programming Language :: Python :: 3.13
Classifier: Programming Language :: Python :: 3.14
Classifier: Topic :: Scientific/Engineering :: Bio-Informatics
Requires-Dist: hvplot (>=0.11.1,<0.12.0)
Requires-Dist: jinja2 (>=3.1.4,<4.0.0)
Requires-Dist: jupyter-bokeh (>=4.0.5,<5.0.0)
Requires-Dist: matplotlib (>=3.9.2,<4.0.0)
Requires-Dist: numpy (>=2.1.2,<3.0.0)
Requires-Dist: openpyxl (>=3.1.5,<4.0.0)
Requires-Dist: ordered-set (>=4.1.0,<5.0.0)
Requires-Dist: pandas (>=2.2.3,<3.0.0)
Requires-Dist: rich (>=13.9.2,<14.0.0)
Requires-Dist: scikit-learn (>=1.7.0,<2.0.0)
Requires-Dist: scipy (>=1.14.1,<2.0.0)
Requires-Dist: seaborn (>=0.13.2,<0.14.0)
Requires-Dist: timple (>=0.1.8,<0.2.0)
Requires-Dist: tqdm (>=4.66.5,<5.0.0)
Project-URL: Homepage, https://nucleus.bnext.bio/
Project-URL: Repository, https://github.com/bnext-bio/nucleus/
